{
  "users": [
    {
      "id": "20604639-e783-469d-bb41-111037bff544",
      "first_name": "Pearline",
      "last_name": "Batz",
      "phone_number": "1-723-675-4769 x4662",
      "email": "Aliza64@hotmail.com",
      "password_hash": "hSry9NmKklDc63k",
      "created_at": "2024-02-23T17:21:33.974Z",
      "updated_at": "2024-09-01T20:56:01.859Z"
    },
    {
      "id": "3949101a-2e36-47eb-b4bd-286066c9b0be",
      "first_name": "Sylvia",
      "last_name": "Frami",
      "phone_number": "1-396-998-9401 x699",
      "email": "Beth.Block69@hotmail.com",
      "password_hash": "Vz_31n0OoxCQvjo",
      "created_at": "2024-07-26T00:54:43.564Z",
      "updated_at": "2024-09-02T03:07:57.586Z"
    },
    {
      "id": "8d4d5742-dbbc-4537-9fd2-eb72b2467f0f",
      "first_name": "Rod",
      "last_name": "Hirthe",
      "phone_number": "268.244.9666",
      "email": "Daphne4@hotmail.com",
      "password_hash": "0EPhRGE_y1WI2a1",
      "created_at": "2024-07-31T07:14:52.971Z",
      "updated_at": "2024-09-01T21:54:24.375Z"
    },
    {
      "id": "e79c3717-6aaf-4b68-a813-1d7711a923bc",
      "first_name": "Gilberto",
      "last_name": "Witting-Bednar",
      "phone_number": "1-877-821-3940 x8760",
      "email": "Leonor.Thiel21@gmail.com",
      "password_hash": "QCYhogAuybXWuRG",
      "created_at": "2024-06-18T19:39:36.193Z",
      "updated_at": "2024-09-01T17:02:11.361Z"
    },
    {
      "id": "ab00cfd2-2b99-4301-8f32-49b54dd2c463",
      "first_name": "Mable",
      "last_name": "Streich",
      "phone_number": "890-559-0669",
      "email": "Ruth_Shanahan-Mraz3@gmail.com",
      "password_hash": "GqPrVVpkMK6odWf",
      "created_at": "2023-09-30T09:46:53.241Z",
      "updated_at": "2024-09-01T14:19:24.460Z"
    },
    {
      "id": "7d8753fe-35db-4210-a092-2fc23eaa8205",
      "first_name": "Celine",
      "last_name": "Powlowski",
      "phone_number": "(618) 972-0391",
      "email": "Jade98@yahoo.com",
      "password_hash": "bSn469P8IS6T2zy",
      "created_at": "2024-02-21T04:46:33.040Z",
      "updated_at": "2024-09-02T06:04:57.073Z"
    },
    {
      "id": "15ce8ac6-343c-46dd-921d-447040d2b5ff",
      "first_name": "Misael",
      "last_name": "Bartell",
      "phone_number": "318-576-4762 x53413",
      "email": "Precious98@hotmail.com",
      "password_hash": "x79BTLEo6eBGF37",
      "created_at": "2024-04-19T22:09:34.724Z",
      "updated_at": "2024-09-01T22:43:46.597Z"
    },
    {
      "id": "4f4cef15-9aca-4d66-a358-a9d7b0afb333",
      "first_name": "Merritt",
      "last_name": "Cormier",
      "phone_number": "1-733-652-0277 x0626",
      "email": "Roman_Wiza@gmail.com",
      "password_hash": "l3I4YQc1OOBUJXs",
      "created_at": "2024-07-14T01:18:49.414Z",
      "updated_at": "2024-09-01T20:35:41.740Z"
    },
    {
      "id": "516a33ce-ab5b-4e93-859b-459918b8e45f",
      "first_name": "Alexandria",
      "last_name": "Beahan-Larson",
      "phone_number": "505.550.4537 x264",
      "email": "Melody_Harvey@hotmail.com",
      "password_hash": "L5Z8itR_ep06zYM",
      "created_at": "2023-09-06T11:02:29.970Z",
      "updated_at": "2024-09-01T21:37:50.448Z"
    },
    {
      "id": "413e12c5-b3c2-4dc9-b813-48402a0dc124",
      "first_name": "Helena",
      "last_name": "Ullrich",
      "phone_number": "674-202-1195 x75111",
      "email": "Noemi.Jast@gmail.com",
      "password_hash": "CI0vtjuWfNIzioy",
      "created_at": "2024-08-07T15:00:18.335Z",
      "updated_at": "2024-09-02T06:21:30.226Z"
    }
  ],
  "addresses": [
    {
      "id": "8a306254-883d-480f-b930-af6fad955325",
      "user_id": "20604639-e783-469d-bb41-111037bff544",
      "street_address": "31545 Donna Plains",
      "city": "East Delphinemouth",
      "province": "Florida",
      "postal_code": "99650"
    },
    {
      "id": "bb970c0e-bbff-4bfa-9c31-207bfdcbfc5e",
      "user_id": "3949101a-2e36-47eb-b4bd-286066c9b0be",
      "street_address": "26492 Francesco Wells",
      "city": "New Helene",
      "province": "Virginia",
      "postal_code": "32255-5197"
    },
    {
      "id": "ebe15efa-6ba3-4ee0-9000-2f433d587f96",
      "user_id": "8d4d5742-dbbc-4537-9fd2-eb72b2467f0f",
      "street_address": "88026 N Maple Street",
      "city": "Port Loucester",
      "province": "Colorado",
      "postal_code": "67815"
    },
    {
      "id": "de12b754-ffef-4ce5-a33a-9588a6919fe2",
      "user_id": "e79c3717-6aaf-4b68-a813-1d7711a923bc",
      "street_address": "887 W Pine Street",
      "city": "Guiseppebury",
      "province": "Kentucky",
      "postal_code": "72150"
    },
    {
      "id": "7b4bd17f-eba4-4f54-8adf-8464883d0176",
      "user_id": "ab00cfd2-2b99-4301-8f32-49b54dd2c463",
      "street_address": "9316 Prosacco Park",
      "city": "Port Susie",
      "province": "Vermont",
      "postal_code": "23244"
    },
    {
      "id": "7e7c52e6-8b2b-4b61-96dd-13d2963a4295",
      "user_id": "7d8753fe-35db-4210-a092-2fc23eaa8205",
      "street_address": "701 Winfield Falls",
      "city": "Port Arthur",
      "province": "Missouri",
      "postal_code": "36402"
    },
    {
      "id": "21e615ea-ac1e-4030-8b8a-6f10fefce9fa",
      "user_id": "15ce8ac6-343c-46dd-921d-447040d2b5ff",
      "street_address": "72106 Yundt Place",
      "city": "Boscoside",
      "province": "West Virginia",
      "postal_code": "37316"
    },
    {
      "id": "c1f10c1b-93ab-4be8-8eda-d2edfed26cc8",
      "user_id": "4f4cef15-9aca-4d66-a358-a9d7b0afb333",
      "street_address": "3835 Clifton Road",
      "city": "Santinamouth",
      "province": "Minnesota",
      "postal_code": "76935"
    },
    {
      "id": "fda0d0c5-6463-49a9-b9f2-7b3a528fc713",
      "user_id": "516a33ce-ab5b-4e93-859b-459918b8e45f",
      "street_address": "97417 The Avenue",
      "city": "South Elda",
      "province": "Connecticut",
      "postal_code": "84016"
    },
    {
      "id": "89240dc9-fa00-4487-8e11-c9c25b90ef83",
      "user_id": "413e12c5-b3c2-4dc9-b813-48402a0dc124",
      "street_address": "3078 Reinger Rapids",
      "city": "Goyettefield",
      "province": "North Dakota",
      "postal_code": "50867-6452"
    }
  ],
  "accounts": [
    {
      "id": "7a550741-633a-45aa-85ff-34ab380bdb85",
      "user_id": "e79c3717-6aaf-4b68-a813-1d7711a923bc",
      "account_type": "User",
      "auth_provider": "Lynch, Ankunding and Wolff",
      "provider_account_id": "fda45e69-23bb-406e-b197-a590d0a78a5b",
      "access_token": "QQe67ex_FB5ju8u",
      "refresh_token": "jOCJW6tn4Olvxwc",
      "token_type": "HVYuGEGM-xcW3M7Uc39Hf",
      "scope": "wSduzZHNhT",
      "id_token": "ll6x3TgQGgeDIFS",
      "session_state": "zMZSoAgIMn",
      "created_at": "2024-05-15T21:31:18.509Z",
      "expires_at": "2025-03-21T08:46:15.839Z",
      "updated_at": "2024-09-02T07:02:20.869Z"
    },
    {
      "id": "5f233bd1-5f9d-42a4-b1a0-6f9a01309d13",
      "user_id": "4f4cef15-9aca-4d66-a358-a9d7b0afb333",
      "account_type": "Admin",
      "auth_provider": "Maggio Inc",
      "provider_account_id": "142a2bc3-a59d-4b30-ba11-ed6634b6e2d7",
      "access_token": "QOWHN5qpPtOLkGN",
      "refresh_token": "aILIgJBtlkAoQR9",
      "token_type": "LA1WjIEwyL2yM2Sg0xfZn",
      "scope": "hMUNmvjkWB",
      "id_token": "XogN6unvfApFjZK",
      "session_state": "DaIBoJombq",
      "created_at": "2024-06-01T22:58:38.995Z",
      "expires_at": "2025-05-11T06:16:53.181Z",
      "updated_at": "2024-09-01T17:01:31.755Z"
    },
    {
      "id": "128be66b-716b-4115-adbe-ea35edc0fe54",
      "user_id": "20604639-e783-469d-bb41-111037bff544",
      "account_type": "User",
      "auth_provider": "Windler, Quitzon and Johnston",
      "provider_account_id": "e0956374-ccd3-4127-a8b3-6b99021505c6",
      "access_token": "H7oXDEOs3CwNZTN",
      "refresh_token": "zxpI1BzHedcuHlP",
      "token_type": "H3JYLJNCa1nX6TgbLG36i",
      "scope": "iCJooFacRX",
      "id_token": "HRzuQa0QHt0j9GC",
      "session_state": "alInHtgttY",
      "created_at": "2023-11-26T04:45:55.848Z",
      "expires_at": "2025-02-21T16:21:05.596Z",
      "updated_at": "2024-09-01T20:55:39.606Z"
    },
    {
      "id": "21b92f60-62be-4076-a3e6-8a69f8ad42d6",
      "user_id": "516a33ce-ab5b-4e93-859b-459918b8e45f",
      "account_type": "User",
      "auth_provider": "Windler LLC",
      "provider_account_id": "be966a95-3cfb-4a12-a30e-ee4423a8f058",
      "access_token": "CdxIetYAJBMuvQf",
      "refresh_token": "XO0iMBTrcCSZO8V",
      "token_type": "hVoyj77_dgbBo3jVQZSCT",
      "scope": "HBVbOopmGH",
      "id_token": "nFpoPpQUHUln3xx",
      "session_state": "MlTZFpwCOC",
      "created_at": "2023-10-07T02:23:12.434Z",
      "expires_at": "2024-11-16T22:40:20.816Z",
      "updated_at": "2024-09-01T14:39:27.073Z"
    },
    {
      "id": "cb46f17d-eeeb-46ae-b862-7acae0eb9f90",
      "user_id": "ab00cfd2-2b99-4301-8f32-49b54dd2c463",
      "account_type": "Admin",
      "auth_provider": "Heller Group",
      "provider_account_id": "051483e9-a39e-4206-81bb-7cb894b32c42",
      "access_token": "glksRL9rBAlIi0M",
      "refresh_token": "A_bIFwpqniDwrfB",
      "token_type": "aIVYzX7GchyLAlVU--vpj",
      "scope": "JdMGtYsDsJ",
      "id_token": "jWnPZEaPizOO6ly",
      "session_state": "WpFkPahBCC",
      "created_at": "2023-09-04T17:17:51.114Z",
      "expires_at": "2025-01-28T20:02:13.119Z",
      "updated_at": "2024-09-02T01:41:19.212Z"
    },
    {
      "id": "df5b2ada-56e8-4a8d-ae03-dc7dd900d2ed",
      "user_id": "7d8753fe-35db-4210-a092-2fc23eaa8205",
      "account_type": "User",
      "auth_provider": "Macejkovic LLC",
      "provider_account_id": "7c808cc7-d2f7-49f3-bf67-47be020d973e",
      "access_token": "P1metG7JCadPUbN",
      "refresh_token": "IqGSPRR910KdE0c",
      "token_type": "BrDkV7lASgsgE3RoXOCIG",
      "scope": "AuwTogDRxz",
      "id_token": "BWhVSkgQiOABds9",
      "session_state": "jyLEyqtiPN",
      "created_at": "2024-03-03T15:35:04.447Z",
      "expires_at": "2024-12-27T05:49:11.638Z",
      "updated_at": "2024-09-02T09:13:22.435Z"
    },
    {
      "id": "8e7aadbb-252c-4cde-b545-2af82904008f",
      "user_id": "3949101a-2e36-47eb-b4bd-286066c9b0be",
      "account_type": "User",
      "auth_provider": "Hirthe - Bednar",
      "provider_account_id": "308daeaa-97bd-4fd1-b9a9-e2bf1d0ef40e",
      "access_token": "gV1d7jhHDiUpFCF",
      "refresh_token": "xkh3nQxdyOMj9Fv",
      "token_type": "5KV55pFfKc_ICuR366-OP",
      "scope": "iFUKBZKgzm",
      "id_token": "4uOj4XJKJ2i6QDd",
      "session_state": "ehYfZeFRUY",
      "created_at": "2023-10-12T15:57:24.885Z",
      "expires_at": "2025-05-01T12:46:20.056Z",
      "updated_at": "2024-09-02T11:27:53.327Z"
    },
    {
      "id": "56771378-6635-4d92-be38-cf0ec1446cb5",
      "user_id": "ab00cfd2-2b99-4301-8f32-49b54dd2c463",
      "account_type": "User",
      "auth_provider": "Bode - Bartell",
      "provider_account_id": "bd2a2a10-c05c-40a7-aaf2-02aed273594f",
      "access_token": "2vB_jP1f9YbcEoJ",
      "refresh_token": "tAJsWMxSJDnHy2G",
      "token_type": "A04KOoX38ZFn98H31sBki",
      "scope": "iwhdfnqQCL",
      "id_token": "LLQUoFhQfwuTnXY",
      "session_state": "QYyWAjqZHw",
      "created_at": "2023-10-21T17:31:09.610Z",
      "expires_at": "2024-11-18T09:52:23.712Z",
      "updated_at": "2024-09-01T14:38:40.345Z"
    },
    {
      "id": "b477764b-cd19-40fd-b68b-ba4c6fff18a7",
      "user_id": "e79c3717-6aaf-4b68-a813-1d7711a923bc",
      "account_type": "User",
      "auth_provider": "Schmidt, Marvin and Bartoletti",
      "provider_account_id": "a7072053-fff5-4592-99b2-b4af6ceb222c",
      "access_token": "dxgPXiolIGapkoq",
      "refresh_token": "qyCoXgpRB7f96i1",
      "token_type": "_1C6S_aaOhVWyYXKHAnZP",
      "scope": "dsbyFcsnbK",
      "id_token": "P0PUxvcF_akEWYI",
      "session_state": "DNWRGhGuap",
      "created_at": "2023-10-18T07:24:50.596Z",
      "expires_at": "2025-02-22T06:10:00.008Z",
      "updated_at": "2024-09-01T21:23:58.574Z"
    },
    {
      "id": "e2265c15-9f42-49c6-966b-92cc83e0919b",
      "user_id": "516a33ce-ab5b-4e93-859b-459918b8e45f",
      "account_type": "User",
      "auth_provider": "Langosh Group",
      "provider_account_id": "e5b01652-0744-4f23-a1eb-fd416686121c",
      "access_token": "0nCiR8ld8m5gj7K",
      "refresh_token": "DfNlYEv_sUogTY4",
      "token_type": "zxwMyiH3lkCA2WPSXc1S5",
      "scope": "XjNqBPSwSI",
      "id_token": "oLVWuxM34B_OcxY",
      "session_state": "cDEaavuGwR",
      "created_at": "2024-01-27T16:02:27.440Z",
      "expires_at": "2024-11-10T05:53:15.645Z",
      "updated_at": "2024-09-02T09:38:12.636Z"
    }
  ],
  "categories": [
    {
      "id": 1,
      "name": "Toys",
      "description": "The Football Is Good For Training And Recreational Purposes",
      "image_url": "https://picsum.photos/seed/afbiAMMIh/640/480"
    },
    {
      "id": 2,
      "name": "Garden",
      "description": "The Football Is Good For Training And Recreational Purposes",
      "image_url": "https://picsum.photos/seed/dRmTL/640/480"
    },
    {
      "id": 3,
      "name": "Clothing",
      "description": "Boston's most advanced compression wear technology increases muscle oxygenation, stabilizes active muscles",
      "image_url": "https://picsum.photos/seed/qLu5A/640/480"
    },
    {
      "id": 4,
      "name": "Kids",
      "description": "The Apollotech B340 is an affordable wireless mouse with reliable connectivity, 12 months battery life and modern design",
      "image_url": "https://picsum.photos/seed/teWE4nRG/640/480"
    },
    {
      "id": 5,
      "name": "Music",
      "description": "Ergonomic executive chair upholstered in bonded black leather and PVC padded seat and back for all-day comfort and support",
      "image_url": "https://picsum.photos/seed/uhMsR/640/480"
    }
  ],
  "products": [
    {
      "id": "1e9ab7f1-16a0-4cfc-a60c-552971a353f2",
      "name": "Licensed Wooden Ball",
      "description": "Andy shoes are designed to keeping in mind durability as well as trends, the most stylish range of shoes & sandals",
      "price": "491",
      "stock": 14,
      "category_id": 1,
      "image_url": "https://picsum.photos/seed/fkHRC/640/480",
      "created_at": "2023-10-30T00:17:07.021Z",
      "updated_at": "2024-09-02T06:21:39.243Z"
    },
    {
      "id": "5de26d6b-decd-4a0f-a43c-c57d2905c43e",
      "name": "Unbranded Plastic Mouse",
      "description": "The slim & simple Maple Gaming Keyboard from Dev Byte comes with a sleek body and 7- Color RGB LED Back-lighting for smart functionality",
      "price": "403",
      "stock": 73,
      "category_id": 1,
      "image_url": "https://picsum.photos/seed/CabH8/640/480",
      "created_at": "2024-01-13T11:20:57.552Z",
      "updated_at": "2024-09-01T12:15:48.325Z"
    },
    {
      "id": "590e9f7c-5c4c-4d4c-9d0a-1e80da0c0549",
      "name": "Small Cotton Car",
      "description": "The Apollotech B340 is an affordable wireless mouse with reliable connectivity, 12 months battery life and modern design",
      "price": "138",
      "stock": 83,
      "category_id": 1,
      "image_url": "https://picsum.photos/seed/IltSu3Z/640/480",
      "created_at": "2023-10-08T21:37:34.545Z",
      "updated_at": "2024-09-02T00:29:01.807Z"
    },
    {
      "id": "46b27347-b5a4-4e1f-8eab-03883c82924f",
      "name": "Elegant Cotton Computer",
      "description": "The Apollotech B340 is an affordable wireless mouse with reliable connectivity, 12 months battery life and modern design",
      "price": "459",
      "stock": 46,
      "category_id": 1,
      "image_url": "https://picsum.photos/seed/7j4wB30/640/480",
      "created_at": "2023-12-16T05:22:09.936Z",
      "updated_at": "2024-09-02T07:34:21.848Z"
    },
    {
      "id": "3fe96b9e-ffa9-465a-8b1f-72559e6143ab",
      "name": "Rustic Steel Cheese",
      "description": "New ABC 13 9370, 13.3, 5th Gen CoreA5-8250U, 8GB RAM, 256GB SSD, power UHD Graphics, OS 10 Home, OS Office A & J 2016",
      "price": "469",
      "stock": 28,
      "category_id": 1,
      "image_url": "https://picsum.photos/seed/FbpyJm/640/480",
      "created_at": "2023-11-13T00:08:00.789Z",
      "updated_at": "2024-09-02T09:30:33.729Z"
    },
    {
      "id": "10935807-e840-4515-9047-7cdb948aa4c2",
      "name": "Incredible Steel Chair",
      "description": "Carbonite web goalkeeper gloves are ergonomically designed to give easy fit",
      "price": "524",
      "stock": 83,
      "category_id": 2,
      "image_url": "https://picsum.photos/seed/RZjIg/640/480",
      "created_at": "2024-07-26T10:34:04.536Z",
      "updated_at": "2024-09-02T05:16:30.099Z"
    },
    {
      "id": "217899f7-2708-42a6-9886-152d1004c4d0",
      "name": "Intelligent Fresh Towels",
      "description": "The Nagasaki Lander is the trademarked name of several series of Nagasaki sport bikes, that started with the 1984 ABC800J",
      "price": "209",
      "stock": 60,
      "category_id": 2,
      "image_url": "https://picsum.photos/seed/W9IZDi/640/480",
      "created_at": "2024-01-18T18:18:10.914Z",
      "updated_at": "2024-09-02T05:48:53.832Z"
    },
    {
      "id": "18a1c4f0-e9d7-4898-b0cc-9fe34194f1b0",
      "name": "Elegant Fresh Table",
      "description": "New range of formal shirts are designed keeping you in mind. With fits and styling that will make you stand apart",
      "price": "444",
      "stock": 18,
      "category_id": 2,
      "image_url": "https://picsum.photos/seed/utmXC/640/480",
      "created_at": "2023-09-07T06:58:39.690Z",
      "updated_at": "2024-09-01T18:59:38.330Z"
    },
    {
      "id": "105fe68d-1daf-470b-a41a-1f5469108bb3",
      "name": "Intelligent Steel Hat",
      "description": "New range of formal shirts are designed keeping you in mind. With fits and styling that will make you stand apart",
      "price": "239",
      "stock": 13,
      "category_id": 2,
      "image_url": "https://picsum.photos/seed/X68i87w9yc/640/480",
      "created_at": "2024-05-01T15:45:30.902Z",
      "updated_at": "2024-09-02T01:28:26.695Z"
    },
    {
      "id": "908356a6-434d-4292-9733-88206472bfaf",
      "name": "Elegant Steel Shirt",
      "description": "Ergonomic executive chair upholstered in bonded black leather and PVC padded seat and back for all-day comfort and support",
      "price": "45",
      "stock": 30,
      "category_id": 2,
      "image_url": "https://picsum.photos/seed/IiebmWEQ/640/480",
      "created_at": "2024-07-30T17:52:04.987Z",
      "updated_at": "2024-09-02T02:13:40.236Z"
    },
    {
      "id": "979d065f-6733-4a13-b9a6-776678a1755f",
      "name": "Intelligent Frozen Salad",
      "description": "New ABC 13 9370, 13.3, 5th Gen CoreA5-8250U, 8GB RAM, 256GB SSD, power UHD Graphics, OS 10 Home, OS Office A & J 2016",
      "price": "107",
      "stock": 48,
      "category_id": 3,
      "image_url": "https://picsum.photos/seed/QFn60hR3A/640/480",
      "created_at": "2024-02-23T19:26:22.732Z",
      "updated_at": "2024-09-01T15:50:08.750Z"
    },
    {
      "id": "66ca1a18-0668-4230-b14e-eb9a7710de18",
      "name": "Incredible Soft Cheese",
      "description": "New range of formal shirts are designed keeping you in mind. With fits and styling that will make you stand apart",
      "price": "370",
      "stock": 32,
      "category_id": 3,
      "image_url": "https://picsum.photos/seed/dT55xj/640/480",
      "created_at": "2023-09-13T04:19:39.238Z",
      "updated_at": "2024-09-02T07:46:32.242Z"
    },
    {
      "id": "b6e6a53a-ecf7-4760-af8d-7fcba8dd50af",
      "name": "Small Steel Chips",
      "description": "The Football Is Good For Training And Recreational Purposes",
      "price": "264",
      "stock": 86,
      "category_id": 3,
      "image_url": "https://picsum.photos/seed/T0Pjh577/640/480",
      "created_at": "2024-07-27T02:38:16.200Z",
      "updated_at": "2024-09-01T15:16:56.458Z"
    },
    {
      "id": "9a4eef29-f402-4936-bdc4-db0ae8c66b3f",
      "name": "Fantastic Cotton Shirt",
      "description": "The slim & simple Maple Gaming Keyboard from Dev Byte comes with a sleek body and 7- Color RGB LED Back-lighting for smart functionality",
      "price": "360",
      "stock": 56,
      "category_id": 3,
      "image_url": "https://picsum.photos/seed/BVxWkn3u/640/480",
      "created_at": "2024-07-17T16:41:11.390Z",
      "updated_at": "2024-09-02T11:19:02.101Z"
    },
    {
      "id": "f42bdac7-2976-4141-94c0-e78822f1042d",
      "name": "Electronic Rubber Cheese",
      "description": "The Football Is Good For Training And Recreational Purposes",
      "price": "414",
      "stock": 81,
      "category_id": 3,
      "image_url": "https://picsum.photos/seed/UaH3QIbw/640/480",
      "created_at": "2024-03-04T10:31:05.899Z",
      "updated_at": "2024-09-02T08:39:27.377Z"
    },
    {
      "id": "77a8fc5d-d8ae-4896-b89a-c4097fe1c63b",
      "name": "Electronic Soft Soap",
      "description": "The automobile layout consists of a front-engine design, with transaxle-type transmissions mounted at the rear of the engine and four wheel drive",
      "price": "405",
      "stock": 51,
      "category_id": 4,
      "image_url": "https://picsum.photos/seed/IspQCoJdSU/640/480",
      "created_at": "2024-03-26T23:30:57.056Z",
      "updated_at": "2024-09-02T05:59:03.310Z"
    },
    {
      "id": "4ca383ec-cb34-44eb-bd72-8ecefec09670",
      "name": "Unbranded Metal Computer",
      "description": "Boston's most advanced compression wear technology increases muscle oxygenation, stabilizes active muscles",
      "price": "71",
      "stock": 29,
      "category_id": 4,
      "image_url": "https://picsum.photos/seed/m6MBMUZti/640/480",
      "created_at": "2024-02-10T23:58:21.615Z",
      "updated_at": "2024-09-02T09:56:05.747Z"
    },
    {
      "id": "7437dc59-a061-4e49-be4e-ebf3971e154e",
      "name": "Sleek Rubber Towels",
      "description": "Ergonomic executive chair upholstered in bonded black leather and PVC padded seat and back for all-day comfort and support",
      "price": "492",
      "stock": 10,
      "category_id": 4,
      "image_url": "https://picsum.photos/seed/FuaqTodusk/640/480",
      "created_at": "2024-03-03T11:48:53.094Z",
      "updated_at": "2024-09-01T14:59:18.746Z"
    },
    {
      "id": "6f3b7e1c-2f36-472b-8805-86e493a83608",
      "name": "Electronic Rubber Pants",
      "description": "Carbonite web goalkeeper gloves are ergonomically designed to give easy fit",
      "price": "483",
      "stock": 98,
      "category_id": 4,
      "image_url": "https://picsum.photos/seed/J4BFDMJ/640/480",
      "created_at": "2023-09-18T07:09:21.837Z",
      "updated_at": "2024-09-01T18:57:15.739Z"
    },
    {
      "id": "88288405-104d-4305-83a7-ecb00ca5bc11",
      "name": "Ergonomic Soft Pizza",
      "description": "The Apollotech B340 is an affordable wireless mouse with reliable connectivity, 12 months battery life and modern design",
      "price": "158",
      "stock": 70,
      "category_id": 4,
      "image_url": "https://picsum.photos/seed/2ijTr/640/480",
      "created_at": "2023-10-31T09:08:50.853Z",
      "updated_at": "2024-09-01T18:25:27.949Z"
    },
    {
      "id": "081b9380-370c-4697-9d2a-a730e0e0211b",
      "name": "Handcrafted Frozen Towels",
      "description": "Ergonomic executive chair upholstered in bonded black leather and PVC padded seat and back for all-day comfort and support",
      "price": "505",
      "stock": 47,
      "category_id": 5,
      "image_url": "https://picsum.photos/seed/pj7xnRJx/640/480",
      "created_at": "2023-10-01T20:29:01.793Z",
      "updated_at": "2024-09-01T15:22:31.503Z"
    },
    {
      "id": "a8be7a9e-67ee-4c9f-a5f9-4bc1cf3c4f71",
      "name": "Sleek Concrete Bacon",
      "description": "Boston's most advanced compression wear technology increases muscle oxygenation, stabilizes active muscles",
      "price": "338",
      "stock": 85,
      "category_id": 5,
      "image_url": "https://picsum.photos/seed/SiXDkURjs/640/480",
      "created_at": "2023-10-18T06:10:56.786Z",
      "updated_at": "2024-09-01T16:44:46.634Z"
    },
    {
      "id": "1cacbab5-0572-47e7-9a30-4df8d9813395",
      "name": "Handmade Wooden Gloves",
      "description": "Andy shoes are designed to keeping in mind durability as well as trends, the most stylish range of shoes & sandals",
      "price": "177",
      "stock": 85,
      "category_id": 5,
      "image_url": "https://picsum.photos/seed/dEnzu/640/480",
      "created_at": "2023-09-27T00:27:24.218Z",
      "updated_at": "2024-09-01T20:31:15.146Z"
    },
    {
      "id": "7e52ad1f-d48f-4be7-812c-76f0471536a4",
      "name": "Modern Wooden Cheese",
      "description": "Ergonomic executive chair upholstered in bonded black leather and PVC padded seat and back for all-day comfort and support",
      "price": "546",
      "stock": 4,
      "category_id": 5,
      "image_url": "https://picsum.photos/seed/RXNE5aUCux/640/480",
      "created_at": "2023-10-02T08:20:46.736Z",
      "updated_at": "2024-09-02T01:45:48.797Z"
    },
    {
      "id": "1d483375-4e59-4e51-a735-fe9e89923018",
      "name": "Elegant Steel Cheese",
      "description": "Carbonite web goalkeeper gloves are ergonomically designed to give easy fit",
      "price": "324",
      "stock": 71,
      "category_id": 5,
      "image_url": "https://picsum.photos/seed/LD1md/640/480",
      "created_at": "2023-11-14T04:11:50.618Z",
      "updated_at": "2024-09-01T16:16:19.067Z"
    }
  ],
  "accordion_items": [
    {
      "id": "4aaa83cc-4183-4e75-a9a9-c420d59ab7eb",
      "product_id": "1e9ab7f1-16a0-4cfc-a60c-552971a353f2",
      "title": "Information",
      "content": "Dolores cubicularis cenaculum. Aggero tabella blandior unde ulterius stabilis debilito angelus vulnero ars. Cubo theca alius benevolentia acervus cilicium ventosus."
    },
    {
      "id": "e320663c-c37c-4e94-abf4-5fac2ab4ac89",
      "product_id": "1e9ab7f1-16a0-4cfc-a60c-552971a353f2",
      "title": "Elegant",
      "content": "Appositus valeo denego abstergo. Adipiscor alo speciosus aliquid victus commodi despecto adiuvo usque. Allatus vobis ullus aspernatur ascisco reiciendis ascisco crebro."
    },
    {
      "id": "e2cb3c8e-0856-4096-973a-30292db21b54",
      "product_id": "5de26d6b-decd-4a0f-a43c-c57d2905c43e",
      "title": "Information",
      "content": "Utrimque tutis deserunt dignissimos quas. Impedit torrens reprehenderit dolorem complectus. Basium possimus corona comedo ducimus delego corporis caries anser."
    },
    {
      "id": "ab7520e7-485d-4238-8669-5747a5d5bacb",
      "product_id": "5de26d6b-decd-4a0f-a43c-c57d2905c43e",
      "title": "Gorgeous",
      "content": "Assumenda una stultus atqui vestrum xiphias deporto tristis depopulo audentia. Verto tardus tenax volo curtus. Volup defaeco demoror."
    },
    {
      "id": "ddfdfb0f-3885-40ee-9ce4-331966b2dafa",
      "product_id": "590e9f7c-5c4c-4d4c-9d0a-1e80da0c0549",
      "title": "Information",
      "content": "Vivo addo officiis adsum aptus. Vobis caute teneo curto tergiversatio. Optio terebro voro statim carus deludo audax."
    },
    {
      "id": "18398662-9353-4cf7-9a8c-08388c83e9dc",
      "product_id": "590e9f7c-5c4c-4d4c-9d0a-1e80da0c0549",
      "title": "Refined",
      "content": "Voluptatibus pel socius aeneus. Sumo caste crebro accedo vulgivagus. Caries avarus praesentium cupio cattus sub coerceo anser itaque cribro."
    },
    {
      "id": "5a485435-ba93-44ea-8830-76745d394817",
      "product_id": "46b27347-b5a4-4e1f-8eab-03883c82924f",
      "title": "Information",
      "content": "Curvo deputo fuga xiphias aureus. Caries caterva textilis astrum. Vinco cohibeo volo accusantium voveo."
    },
    {
      "id": "ff774e1c-108b-44fe-ad48-2ff9f26a46ea",
      "product_id": "46b27347-b5a4-4e1f-8eab-03883c82924f",
      "title": "Awesome",
      "content": "Amaritudo amita aranea cometes aequus adfero voluntarius dedico doloribus. Antepono confido dolores vulgaris rerum conicio esse auxilium tremo. Ullam tenus vereor."
    },
    {
      "id": "573dd2f6-9969-4396-aba3-46e700daf7b2",
      "product_id": "3fe96b9e-ffa9-465a-8b1f-72559e6143ab",
      "title": "Information",
      "content": "Conservo beneficium patruus. Bene minima timor explicabo cerno ab arcesso. Placeat cupressus theca ventosus vinculum certus ipsam corroboro delicate tepidus."
    },
    {
      "id": "676218be-93b7-4318-9788-ef60d8b37c5a",
      "product_id": "3fe96b9e-ffa9-465a-8b1f-72559e6143ab",
      "title": "Tasty",
      "content": "Suffoco terror inventore umerus desparatus synagoga amplitudo vinculum. Desipio ara supplanto perferendis vinculum cubicularis. Delicate derideo speculum careo decipio quos usus."
    },
    {
      "id": "91b2c054-7d9b-481b-bd37-92e5bf754ec1",
      "product_id": "10935807-e840-4515-9047-7cdb948aa4c2",
      "title": "Information",
      "content": "Tepesco pectus currus bardus praesentium veritatis. Centum benigne tristis timor decimus tonsor qui curatio cuius. Vitiosus omnis video articulus confero bos tergiversatio pauci."
    },
    {
      "id": "5267d4d4-dbef-4acb-bc90-8fca8612c250",
      "product_id": "10935807-e840-4515-9047-7cdb948aa4c2",
      "title": "Bespoke",
      "content": "Arcus assumenda bonus angustus suffragium collum decimus. Aequitas itaque ars careo velut. Viduo vilicus audeo vesper."
    },
    {
      "id": "a3dc7fee-eaac-4bac-b262-0566d9e3acdf",
      "product_id": "217899f7-2708-42a6-9886-152d1004c4d0",
      "title": "Information",
      "content": "Certe cicuta vinitor timor ver. Conforto eos aro cetera viscus damnatio saepe. Decipio amiculum tempora cumque aspicio cursim votum."
    },
    {
      "id": "469b3fb4-9a8c-4fac-84a3-95e69add2bf5",
      "product_id": "217899f7-2708-42a6-9886-152d1004c4d0",
      "title": "Handmade",
      "content": "Trado theca minus cupiditas trucido uredo accusamus reiciendis cito. Adimpleo deripio vomer earum stella copiose subseco. Confero dens nesciunt nobis attero facere triduana veritatis angelus comis."
    },
    {
      "id": "a9e86419-e957-44c5-a437-c23d1a5ca696",
      "product_id": "18a1c4f0-e9d7-4898-b0cc-9fe34194f1b0",
      "title": "Information",
      "content": "Agnitio cattus aurum tabernus molestias validus supplanto. Suscipio ultra curia atrocitas coaegresco cimentarius ancilla triduana adeo xiphias. Addo aegrotatio occaecati deprimo thesaurus vesper cognatus defleo cernuus."
    },
    {
      "id": "8dd113f5-a5e8-41f5-b816-fb4e62b71c03",
      "product_id": "18a1c4f0-e9d7-4898-b0cc-9fe34194f1b0",
      "title": "Tasty",
      "content": "Itaque cometes tot attonbitus surgo venustas admiratio tunc ter. Quisquam cogo vere crastinus vinitor votum subito eum. Abstergo canto quas iusto defero vestrum comptus."
    },
    {
      "id": "7a34919e-ab08-46cf-8fcc-366cbb1f621f",
      "product_id": "105fe68d-1daf-470b-a41a-1f5469108bb3",
      "title": "Information",
      "content": "Suasoria valens minus theologus. Derelinquo solvo umquam beatae caste templum. Subvenio dedico arma vicinus clibanus adfero accendo ater cattus."
    },
    {
      "id": "0c05efc7-8a46-450c-a377-1c543639bc1e",
      "product_id": "105fe68d-1daf-470b-a41a-1f5469108bb3",
      "title": "Ergonomic",
      "content": "Bis repellendus pectus benigne quas adversus. Ea vae cursus arma tam laudantium labore copiose. Bibo tabella decor."
    },
    {
      "id": "a0b5358c-136a-49e4-9f8e-1da38ab77c54",
      "product_id": "908356a6-434d-4292-9733-88206472bfaf",
      "title": "Information",
      "content": "Abscido timor delectatio verto repellat repudiandae. Cornu adversus alioqui cupressus. Capio conservo viriliter admoneo adipiscor argentum sulum varius mollitia itaque."
    },
    {
      "id": "c9812bd6-ce17-4b2f-999a-ccf89774a359",
      "product_id": "908356a6-434d-4292-9733-88206472bfaf",
      "title": "Tasty",
      "content": "Aut conicio cui venio voluptatum ceno urbanus aegrotatio caterva. Benigne vester tredecim cavus ullam expedita dedico. Illum casus avarus deprimo creta canis audeo."
    },
    {
      "id": "06b90728-1c74-47c2-a112-d72eacfdefe0",
      "product_id": "979d065f-6733-4a13-b9a6-776678a1755f",
      "title": "Information",
      "content": "Templum animi contra. Degenero careo triumphus summa caterva cubitum. Velit doloribus demitto esse cernuus aveho ver adsidue verecundia tergo."
    },
    {
      "id": "b1296e9d-34dd-4d5a-8f94-efe4a5bf7f3c",
      "product_id": "979d065f-6733-4a13-b9a6-776678a1755f",
      "title": "Incredible",
      "content": "Absum temptatio alveus tergum nemo cribro aptus conatus. Sed tondeo fugiat vestigium sulum arto. Cruentus vergo vis subnecto vitae aestivus consequuntur quibusdam cerno casso."
    },
    {
      "id": "7b9ef449-b1aa-40da-b07e-c23eed298df7",
      "product_id": "66ca1a18-0668-4230-b14e-eb9a7710de18",
      "title": "Information",
      "content": "Creber esse dens possimus congregatio attero comedo adnuo tutamen patior. Conventus cursim tero sono admoveo tardus adulatio alius. Cado velociter textor cribro sol aeneus cunae."
    },
    {
      "id": "7290d482-ad6f-4038-9701-16f5f763d65f",
      "product_id": "66ca1a18-0668-4230-b14e-eb9a7710de18",
      "title": "Fantastic",
      "content": "Adfectus templum cras curiositas ventosus officiis arto. Sunt cum truculenter abduco carbo crastinus. Ustilo tres turpis coepi supellex somnus."
    },
    {
      "id": "a4aaefc8-f4f0-42ed-82f5-a59a2a61f29a",
      "product_id": "b6e6a53a-ecf7-4760-af8d-7fcba8dd50af",
      "title": "Information",
      "content": "Depopulo capto odio defessus decens acer. Advoco acervus temptatio bibo commodo arca catena voluptatem. Blanditiis vulgivagus quis."
    },
    {
      "id": "89e9d3e8-23d2-479b-a54b-6b1293018d9c",
      "product_id": "b6e6a53a-ecf7-4760-af8d-7fcba8dd50af",
      "title": "Ergonomic",
      "content": "Undique acies cresco aggero. Repellat aegre curto. Temporibus sophismata audio thema cunabula antiquus aliquid compono astrum."
    },
    {
      "id": "9de7ce61-33a7-4e72-a2ee-067adab9ad1a",
      "product_id": "9a4eef29-f402-4936-bdc4-db0ae8c66b3f",
      "title": "Information",
      "content": "Tabgo vomer ultra adopto commodi cedo deinde. Virtus volutabrum comitatus absque congregatio aufero. Libero derelinquo suppellex virga adeptio cursus dens distinctio denique."
    },
    {
      "id": "296341fd-4d89-429b-b1d1-518f11f27e7b",
      "product_id": "9a4eef29-f402-4936-bdc4-db0ae8c66b3f",
      "title": "Rustic",
      "content": "Civis facilis deinde cum debitis tergeo appositus deserunt abbas. Approbo dolor caries crepusculum considero venustas. Cupiditas ad thalassinus trepide benevolentia suasoria corporis nostrum."
    },
    {
      "id": "40e0803a-5001-401c-9977-06cb1c434539",
      "product_id": "f42bdac7-2976-4141-94c0-e78822f1042d",
      "title": "Information",
      "content": "Abutor vero summopere stips armarium centum velociter talio. Cumque capitulus voco. Adulescens cultellus cibus subseco bis tendo subiungo illo debilito."
    },
    {
      "id": "d71a9571-2a32-41a3-8790-14d9ce4773f3",
      "product_id": "f42bdac7-2976-4141-94c0-e78822f1042d",
      "title": "Modern",
      "content": "Vorago conor suffragium addo tempore expedita. At tondeo conturbo clarus alii amitto deorsum aggredior. Tendo casus autus curso nostrum."
    },
    {
      "id": "d227dfb6-c69e-4134-9730-ab05a79deb9b",
      "product_id": "77a8fc5d-d8ae-4896-b89a-c4097fe1c63b",
      "title": "Information",
      "content": "Accusator aequitas auctor. Claudeo appositus consectetur tero hic derelinquo argumentum compello. Comptus animadverto abduco ager vetus antepono."
    },
    {
      "id": "61698426-11e4-46ee-a5f4-84eadc573baf",
      "product_id": "77a8fc5d-d8ae-4896-b89a-c4097fe1c63b",
      "title": "Incredible",
      "content": "Tempore comparo eligendi thorax tabesco amet facere officia sortitus. Comminor repellat utrum ubi confero benigne vester. Caute exercitationem voluptate calamitas illo tredecim arceo dignissimos."
    },
    {
      "id": "1847747a-01fb-486a-b96c-8ab50ec042e6",
      "product_id": "4ca383ec-cb34-44eb-bd72-8ecefec09670",
      "title": "Information",
      "content": "Maiores natus temptatio dicta averto validus argentum caries. Speculum blandior vapulus. Annus adduco alias."
    },
    {
      "id": "f397eff0-0b45-4bd6-a571-0e0e87edaeb0",
      "product_id": "4ca383ec-cb34-44eb-bd72-8ecefec09670",
      "title": "Practical",
      "content": "Adaugeo degusto capto itaque damno tenus alienus. Defendo pectus artificiose molestias commemoro aliquam. Calco abduco arceo victus cupio."
    },
    {
      "id": "528a520e-49b6-4a44-9ad0-1e2ecc8d080c",
      "product_id": "7437dc59-a061-4e49-be4e-ebf3971e154e",
      "title": "Information",
      "content": "Corporis cuppedia quod averto tardus substantia spectaculum. Denuncio demonstro tergiversatio tabesco nihil vito. Ager earum nam vulariter tripudio arceo."
    },
    {
      "id": "61963905-ac5c-43e6-9b10-c2ed83cd8e20",
      "product_id": "7437dc59-a061-4e49-be4e-ebf3971e154e",
      "title": "Electronic",
      "content": "Territo exercitationem exercitationem necessitatibus reprehenderit fuga deleo facere. Aliqua vulpes bonus tenax claustrum adaugeo praesentium sol. Ad conatus vergo sublime cumque arbitro contigo."
    },
    {
      "id": "ec988a8d-8658-449e-bf64-895cfee204f3",
      "product_id": "6f3b7e1c-2f36-472b-8805-86e493a83608",
      "title": "Information",
      "content": "Aegre studio vinum tunc. Deludo aptus cura synagoga coma in curvo bardus delicate. Texo clamo subvenio vito basium varietas adimpleo adhuc."
    },
    {
      "id": "be9e6597-e176-4504-9d6a-2712aed76476",
      "product_id": "6f3b7e1c-2f36-472b-8805-86e493a83608",
      "title": "Ergonomic",
      "content": "Conforto quis sub apostolus thema adsuesco tres. Velum doloribus demitto annus patruus. Molestiae temporibus utroque suppellex cruentus vigor peccatus accedo."
    },
    {
      "id": "60507012-229c-4936-957b-b20d2f95a53a",
      "product_id": "88288405-104d-4305-83a7-ecb00ca5bc11",
      "title": "Information",
      "content": "Cui sequi amor subseco. Barba usus stultus thesis iusto. Tego expedita culpa vel quae tredecim ducimus adsum appositus."
    },
    {
      "id": "f46f90f2-081d-479d-a6ba-6ec0efba5b23",
      "product_id": "88288405-104d-4305-83a7-ecb00ca5bc11",
      "title": "Awesome",
      "content": "Repudiandae paulatim cruentus. Communis civis quisquam carbo defendo adulatio. Cito apostolus cibus."
    },
    {
      "id": "e5f878f4-a543-4563-a7d4-5b251ffeb226",
      "product_id": "081b9380-370c-4697-9d2a-a730e0e0211b",
      "title": "Information",
      "content": "Defero substantia comedo textilis demum ante concido crur arcus. Varietas defleo virgo confido eius tristis angelus. Cursim dicta fugit damno carpo tardus amoveo deserunt fugit."
    },
    {
      "id": "6f910214-1e65-424a-835e-ae94a35692fe",
      "product_id": "081b9380-370c-4697-9d2a-a730e0e0211b",
      "title": "Elegant",
      "content": "Tam similique tui antiquus tamdiu. Cuius vulticulus ipsa demergo virgo chirographum curo voco. Angustus ager vobis conicio tantillus curriculum in confido."
    },
    {
      "id": "5291505e-20ed-4c4b-8ba5-0840954d577b",
      "product_id": "a8be7a9e-67ee-4c9f-a5f9-4bc1cf3c4f71",
      "title": "Information",
      "content": "Utilis officia ipsam cunabula temeritas uxor vinculum statim alius varietas. Maxime perferendis damno nesciunt circumvenio causa supellex denuncio. Valetudo aufero cursim creber articulus calcar tibi velut verus."
    },
    {
      "id": "742acc33-e618-4369-8971-416524851d2f",
      "product_id": "a8be7a9e-67ee-4c9f-a5f9-4bc1cf3c4f71",
      "title": "Unbranded",
      "content": "Versus quisquam conventus ipsam atqui. Convoco ex tenuis cotidie. Talis reprehenderit arguo conturbo."
    },
    {
      "id": "0c353cdd-b619-4125-875f-5544afa68f2d",
      "product_id": "1cacbab5-0572-47e7-9a30-4df8d9813395",
      "title": "Information",
      "content": "Stultus tredecim adeptio vivo sonitus ascisco tersus. Creator cum cuius tredecim auxilium decumbo. Aureus animi suffoco inflammatio defungo illo iusto thesis aestas magni."
    },
    {
      "id": "c6667633-ff8c-4a3c-b469-513d02ed4b03",
      "product_id": "1cacbab5-0572-47e7-9a30-4df8d9813395",
      "title": "Handmade",
      "content": "Tersus vapulus adulatio correptius conatus. Curo tenax suffoco curiositas administratio. Articulus pauci abbas custodia exercitationem villa viscus."
    },
    {
      "id": "a6a4124e-7bf1-452f-aa54-04fda43328b2",
      "product_id": "7e52ad1f-d48f-4be7-812c-76f0471536a4",
      "title": "Information",
      "content": "Viridis textilis cito ventus socius thema defetiscor derelinquo totus valens. Cupiditas avarus admoneo dolores currus suscipit. Alioqui vesica tabula patruus advenio repudiandae."
    },
    {
      "id": "1254d41a-fd65-4cc1-8aa1-af36d376a4a0",
      "product_id": "7e52ad1f-d48f-4be7-812c-76f0471536a4",
      "title": "Recycled",
      "content": "Basium clam thorax usus sufficio ante urbs corrupti. Amita fugit demonstro. Appono utrimque supra utique carus."
    },
    {
      "id": "eacf6e36-ed0e-49e5-969c-f8fd66494ea3",
      "product_id": "1d483375-4e59-4e51-a735-fe9e89923018",
      "title": "Information",
      "content": "Excepturi torrens spiritus vindico vito caput suppono possimus. Aptus taceo enim tibi. Thesis una pauci laborum amaritudo summisse suus delinquo aduro."
    },
    {
      "id": "0e037638-09f3-4898-84e1-b59271c579fa",
      "product_id": "1d483375-4e59-4e51-a735-fe9e89923018",
      "title": "Modern",
      "content": "Molestiae deficio candidus acer cultellus pel sapiente creo animus. Arbustum vetus curvo quidem. Chirographum aperiam tremo una sponte."
    }
  ],
  "orders": [
    {
      "id": "bb0db3f1-63cd-42c8-a975-41fd769a9002",
      "user_id": "8d4d5742-dbbc-4537-9fd2-eb72b2467f0f",
      "status": "Done",
      "payment_information": "6759-8901-1541-0114",
      "total_price": 1770,
      "created_at": "2024-01-25T23:35:25.954Z",
      "updated_at": "2024-09-01T15:10:42.611Z"
    },
    {
      "id": "40996150-5d57-484e-b528-9253108f5612",
      "user_id": "e79c3717-6aaf-4b68-a813-1d7711a923bc",
      "status": "Pending",
      "payment_information": "3529-0073-8133-5596",
      "total_price": 3472,
      "created_at": "2023-10-11T06:47:12.262Z",
      "updated_at": "2024-09-01T20:04:39.341Z"
    },
    {
      "id": "4e9fc4e5-2739-4408-80bd-eab43e459676",
      "user_id": "e79c3717-6aaf-4b68-a813-1d7711a923bc",
      "status": "Paid",
      "payment_information": "6011-9566-4746-3808",
      "total_price": 2730,
      "created_at": "2024-02-18T22:19:54.771Z",
      "updated_at": "2024-09-02T02:40:18.463Z"
    },
    {
      "id": "355a6def-15c4-42a1-847d-ed0752bf2edc",
      "user_id": "20604639-e783-469d-bb41-111037bff544",
      "status": "Pending",
      "payment_information": "6011-6257-3782-0617-7553",
      "total_price": 1230,
      "created_at": "2024-08-31T04:22:30.078Z",
      "updated_at": "2024-09-02T09:10:46.688Z"
    },
    {
      "id": "e3a88b21-4601-43c9-87d3-104198f2e1f4",
      "user_id": "ab00cfd2-2b99-4301-8f32-49b54dd2c463",
      "status": "Pending",
      "payment_information": "6304-3552-8010-3001",
      "total_price": 3117,
      "created_at": "2024-07-09T05:02:52.841Z",
      "updated_at": "2024-09-01T19:03:08.305Z"
    },
    {
      "id": "77fde7ba-4df8-4843-932c-56f17d7a0c50",
      "user_id": "e79c3717-6aaf-4b68-a813-1d7711a923bc",
      "status": "Canceled",
      "payment_information": "3528-7693-3981-3245",
      "total_price": 284,
      "created_at": "2024-06-07T01:18:40.818Z",
      "updated_at": "2024-09-02T03:08:14.273Z"
    },
    {
      "id": "4ae76d03-a2a0-4d18-854e-9d39dfa7e6cd",
      "user_id": "4f4cef15-9aca-4d66-a358-a9d7b0afb333",
      "status": "Paid",
      "payment_information": "4537812950225",
      "total_price": 1473,
      "created_at": "2024-07-23T07:25:56.023Z",
      "updated_at": "2024-09-01T14:47:15.524Z"
    },
    {
      "id": "756a12c8-89d1-4851-b909-1285d8bc3356",
      "user_id": "516a33ce-ab5b-4e93-859b-459918b8e45f",
      "status": "Canceled",
      "payment_information": "3031-395604-3716",
      "total_price": 2928,
      "created_at": "2024-08-24T21:46:25.700Z",
      "updated_at": "2024-09-01T15:56:16.463Z"
    },
    {
      "id": "953974da-50f8-4db7-8d0e-9f4ea613428b",
      "user_id": "e79c3717-6aaf-4b68-a813-1d7711a923bc",
      "status": "Canceled",
      "payment_information": "6011-1868-3286-9177",
      "total_price": 4901,
      "created_at": "2023-11-28T08:15:51.579Z",
      "updated_at": "2024-09-02T06:04:47.959Z"
    },
    {
      "id": "13f4d769-c456-4e27-8b38-2ecd326adc3c",
      "user_id": "3949101a-2e36-47eb-b4bd-286066c9b0be",
      "status": "Canceled",
      "payment_information": "3528-9616-1529-7199",
      "total_price": 276,
      "created_at": "2024-07-24T19:08:40.664Z",
      "updated_at": "2024-09-01T18:57:00.401Z"
    }
  ],
  "order_items": [
    {
      "id": "132f2401-86be-4250-b721-63c0b8e2bcc2",
      "order_id": "bb0db3f1-63cd-42c8-a975-41fd769a9002",
      "product_id": "88288405-104d-4305-83a7-ecb00ca5bc11",
      "name": "Ergonomic Soft Pizza",
      "image_url": "https://picsum.photos/seed/2ijTr/640/480",
      "price": 316,
      "quantity": 2
    },
    {
      "id": "b2e87058-082b-4c9b-8bb3-7d127af90953",
      "order_id": "bb0db3f1-63cd-42c8-a975-41fd769a9002",
      "product_id": "18a1c4f0-e9d7-4898-b0cc-9fe34194f1b0",
      "name": "Elegant Fresh Table",
      "image_url": "https://picsum.photos/seed/utmXC/640/480",
      "price": 444,
      "quantity": 1
    },
    {
      "id": "266409a9-3a2e-4883-b06c-501779ff907f",
      "order_id": "bb0db3f1-63cd-42c8-a975-41fd769a9002",
      "product_id": "081b9380-370c-4697-9d2a-a730e0e0211b",
      "name": "Handcrafted Frozen Towels",
      "image_url": "https://picsum.photos/seed/pj7xnRJx/640/480",
      "price": 1010,
      "quantity": 2
    },
    {
      "id": "0d040e46-ded3-4b61-ab4b-5184f8b4e6cb",
      "order_id": "40996150-5d57-484e-b528-9253108f5612",
      "product_id": "9a4eef29-f402-4936-bdc4-db0ae8c66b3f",
      "name": "Fantastic Cotton Shirt",
      "image_url": "https://picsum.photos/seed/BVxWkn3u/640/480",
      "price": 1800,
      "quantity": 5
    },
    {
      "id": "801e3819-eb55-49a7-ba91-36c3efcddcc2",
      "order_id": "40996150-5d57-484e-b528-9253108f5612",
      "product_id": "217899f7-2708-42a6-9886-152d1004c4d0",
      "name": "Intelligent Fresh Towels",
      "image_url": "https://picsum.photos/seed/W9IZDi/640/480",
      "price": 836,
      "quantity": 4
    },
    {
      "id": "2d94d5a4-ac42-49b9-b9a6-449ac8bdae3e",
      "order_id": "40996150-5d57-484e-b528-9253108f5612",
      "product_id": "217899f7-2708-42a6-9886-152d1004c4d0",
      "name": "Intelligent Fresh Towels",
      "image_url": "https://picsum.photos/seed/W9IZDi/640/480",
      "price": 836,
      "quantity": 4
    },
    {
      "id": "0e984ed1-6ca1-4733-8e12-5af79e13ffd0",
      "order_id": "4e9fc4e5-2739-4408-80bd-eab43e459676",
      "product_id": "7e52ad1f-d48f-4be7-812c-76f0471536a4",
      "name": "Modern Wooden Cheese",
      "image_url": "https://picsum.photos/seed/RXNE5aUCux/640/480",
      "price": 2730,
      "quantity": 5
    },
    {
      "id": "d16a40aa-9f15-4475-a1d9-03284f9fea25",
      "order_id": "355a6def-15c4-42a1-847d-ed0752bf2edc",
      "product_id": "590e9f7c-5c4c-4d4c-9d0a-1e80da0c0549",
      "name": "Small Cotton Car",
      "image_url": "https://picsum.photos/seed/IltSu3Z/640/480",
      "price": 138,
      "quantity": 1
    },
    {
      "id": "e9fc60ed-804a-4be9-b122-0909e668a047",
      "order_id": "355a6def-15c4-42a1-847d-ed0752bf2edc",
      "product_id": "7e52ad1f-d48f-4be7-812c-76f0471536a4",
      "name": "Modern Wooden Cheese",
      "image_url": "https://picsum.photos/seed/RXNE5aUCux/640/480",
      "price": 1092,
      "quantity": 2
    },
    {
      "id": "094aa0af-e0d0-46bd-8fad-1a1dccd8f247",
      "order_id": "e3a88b21-4601-43c9-87d3-104198f2e1f4",
      "product_id": "7e52ad1f-d48f-4be7-812c-76f0471536a4",
      "name": "Modern Wooden Cheese",
      "image_url": "https://picsum.photos/seed/RXNE5aUCux/640/480",
      "price": 1092,
      "quantity": 2
    },
    {
      "id": "249deb39-bbcd-46db-b299-7502925a120f",
      "order_id": "e3a88b21-4601-43c9-87d3-104198f2e1f4",
      "product_id": "77a8fc5d-d8ae-4896-b89a-c4097fe1c63b",
      "name": "Electronic Soft Soap",
      "image_url": "https://picsum.photos/seed/IspQCoJdSU/640/480",
      "price": 2025,
      "quantity": 5
    },
    {
      "id": "b881b937-0f1b-4b7c-8ecf-44c272b82efc",
      "order_id": "77fde7ba-4df8-4843-932c-56f17d7a0c50",
      "product_id": "4ca383ec-cb34-44eb-bd72-8ecefec09670",
      "name": "Unbranded Metal Computer",
      "image_url": "https://picsum.photos/seed/m6MBMUZti/640/480",
      "price": 284,
      "quantity": 4
    },
    {
      "id": "1a1391d6-214c-4b13-976a-320786d22498",
      "order_id": "4ae76d03-a2a0-4d18-854e-9d39dfa7e6cd",
      "product_id": "1e9ab7f1-16a0-4cfc-a60c-552971a353f2",
      "name": "Licensed Wooden Ball",
      "image_url": "https://picsum.photos/seed/fkHRC/640/480",
      "price": 1473,
      "quantity": 3
    },
    {
      "id": "19645f4c-1a86-4d9f-b99f-689a48011004",
      "order_id": "756a12c8-89d1-4851-b909-1285d8bc3356",
      "product_id": "46b27347-b5a4-4e1f-8eab-03883c82924f",
      "name": "Elegant Cotton Computer",
      "image_url": "https://picsum.photos/seed/7j4wB30/640/480",
      "price": 459,
      "quantity": 1
    },
    {
      "id": "13e5ff05-4306-4b71-b0ca-6fadb86df3cd",
      "order_id": "756a12c8-89d1-4851-b909-1285d8bc3356",
      "product_id": "18a1c4f0-e9d7-4898-b0cc-9fe34194f1b0",
      "name": "Elegant Fresh Table",
      "image_url": "https://picsum.photos/seed/utmXC/640/480",
      "price": 444,
      "quantity": 1
    },
    {
      "id": "834fbc3b-8703-46cc-aa8f-fa4690f4cf89",
      "order_id": "756a12c8-89d1-4851-b909-1285d8bc3356",
      "product_id": "77a8fc5d-d8ae-4896-b89a-c4097fe1c63b",
      "name": "Electronic Soft Soap",
      "image_url": "https://picsum.photos/seed/IspQCoJdSU/640/480",
      "price": 2025,
      "quantity": 5
    },
    {
      "id": "e0927afd-d8e7-4f2c-8d7e-0c394b80c20a",
      "order_id": "953974da-50f8-4db7-8d0e-9f4ea613428b",
      "product_id": "f42bdac7-2976-4141-94c0-e78822f1042d",
      "name": "Electronic Rubber Cheese",
      "image_url": "https://picsum.photos/seed/UaH3QIbw/640/480",
      "price": 2070,
      "quantity": 5
    },
    {
      "id": "e34f27fa-f156-48fd-9a56-a6ac9377b498",
      "order_id": "953974da-50f8-4db7-8d0e-9f4ea613428b",
      "product_id": "5de26d6b-decd-4a0f-a43c-c57d2905c43e",
      "name": "Unbranded Plastic Mouse",
      "image_url": "https://picsum.photos/seed/CabH8/640/480",
      "price": 806,
      "quantity": 2
    },
    {
      "id": "d0f2e209-c8f7-466a-8bf5-8b24f68bed54",
      "order_id": "953974da-50f8-4db7-8d0e-9f4ea613428b",
      "product_id": "77a8fc5d-d8ae-4896-b89a-c4097fe1c63b",
      "name": "Electronic Soft Soap",
      "image_url": "https://picsum.photos/seed/IspQCoJdSU/640/480",
      "price": 2025,
      "quantity": 5
    },
    {
      "id": "f0ae0bc1-3ef0-4c61-bc44-edbd35c379fe",
      "order_id": "13f4d769-c456-4e27-8b38-2ecd326adc3c",
      "product_id": "590e9f7c-5c4c-4d4c-9d0a-1e80da0c0549",
      "name": "Small Cotton Car",
      "image_url": "https://picsum.photos/seed/IltSu3Z/640/480",
      "price": 276,
      "quantity": 2
    }
  ],
  "carts": [
    {
      "id": "9da1c9f7-9d20-4310-a023-0eeb94863e77",
      "user_id": "15ce8ac6-343c-46dd-921d-447040d2b5ff",
      "created_at": "2024-07-15T12:36:03.685Z",
      "updated_at": "2024-09-01T16:43:43.859Z"
    },
    {
      "id": "38665544-ea58-48dc-9c51-3944ac9d283f",
      "user_id": "e79c3717-6aaf-4b68-a813-1d7711a923bc",
      "created_at": "2023-11-10T15:06:44.989Z",
      "updated_at": "2024-09-02T02:13:00.368Z"
    },
    {
      "id": "27c4da84-58d9-486c-9849-f6f660d25394",
      "user_id": "15ce8ac6-343c-46dd-921d-447040d2b5ff",
      "created_at": "2023-11-18T04:53:24.068Z",
      "updated_at": "2024-09-02T03:12:08.394Z"
    },
    {
      "id": "e270a02a-c6a7-400d-bb8f-693f8a6c1adf",
      "user_id": "8d4d5742-dbbc-4537-9fd2-eb72b2467f0f",
      "created_at": "2024-04-18T23:23:03.734Z",
      "updated_at": "2024-09-01T12:41:35.037Z"
    },
    {
      "id": "d207be54-0700-4eea-a270-15a31d8a24e7",
      "user_id": "15ce8ac6-343c-46dd-921d-447040d2b5ff",
      "created_at": "2023-09-06T23:29:53.636Z",
      "updated_at": "2024-09-02T05:12:52.269Z"
    }
  ],
  "cart_items": [
    {
      "id": "2c9bf265-31c0-4553-995c-ff800528b706",
      "cart_id": "9da1c9f7-9d20-4310-a023-0eeb94863e77",
      "product_id": "6f3b7e1c-2f36-472b-8805-86e493a83608",
      "name": "Electronic Rubber Pants",
      "image_url": "https://picsum.photos/seed/J4BFDMJ/640/480",
      "price": "483",
      "quantity": 8
    },
    {
      "id": "a7b6845e-dfe5-4e37-a91d-e0b00fbf517b",
      "cart_id": "9da1c9f7-9d20-4310-a023-0eeb94863e77",
      "product_id": "10935807-e840-4515-9047-7cdb948aa4c2",
      "name": "Incredible Steel Chair",
      "image_url": "https://picsum.photos/seed/RZjIg/640/480",
      "price": "524",
      "quantity": 5
    },
    {
      "id": "ec23ed21-b0db-4cee-9f6d-a8ae54e7760d",
      "cart_id": "9da1c9f7-9d20-4310-a023-0eeb94863e77",
      "product_id": "105fe68d-1daf-470b-a41a-1f5469108bb3",
      "name": "Intelligent Steel Hat",
      "image_url": "https://picsum.photos/seed/X68i87w9yc/640/480",
      "price": "239",
      "quantity": 2
    },
    {
      "id": "64f9dd0f-ae73-425d-a26d-83bb1264c7f0",
      "cart_id": "9da1c9f7-9d20-4310-a023-0eeb94863e77",
      "product_id": "7437dc59-a061-4e49-be4e-ebf3971e154e",
      "name": "Sleek Rubber Towels",
      "image_url": "https://picsum.photos/seed/FuaqTodusk/640/480",
      "price": "492",
      "quantity": 8
    },
    {
      "id": "451f9a8d-4828-433c-a892-83c1b58c2379",
      "cart_id": "9da1c9f7-9d20-4310-a023-0eeb94863e77",
      "product_id": "88288405-104d-4305-83a7-ecb00ca5bc11",
      "name": "Ergonomic Soft Pizza",
      "image_url": "https://picsum.photos/seed/2ijTr/640/480",
      "price": "158",
      "quantity": 9
    },
    {
      "id": "694a0666-ff7b-4e3f-bbe8-34a85c30bb92",
      "cart_id": "38665544-ea58-48dc-9c51-3944ac9d283f",
      "product_id": "1d483375-4e59-4e51-a735-fe9e89923018",
      "name": "Elegant Steel Cheese",
      "image_url": "https://picsum.photos/seed/LD1md/640/480",
      "price": "324",
      "quantity": 7
    },
    {
      "id": "829eeea7-6723-4cae-9ad4-74a34f25f376",
      "cart_id": "38665544-ea58-48dc-9c51-3944ac9d283f",
      "product_id": "217899f7-2708-42a6-9886-152d1004c4d0",
      "name": "Intelligent Fresh Towels",
      "image_url": "https://picsum.photos/seed/W9IZDi/640/480",
      "price": "209",
      "quantity": 9
    },
    {
      "id": "f4246197-7c04-418e-8d09-9a93b1c335c3",
      "cart_id": "38665544-ea58-48dc-9c51-3944ac9d283f",
      "product_id": "7e52ad1f-d48f-4be7-812c-76f0471536a4",
      "name": "Modern Wooden Cheese",
      "image_url": "https://picsum.photos/seed/RXNE5aUCux/640/480",
      "price": "546",
      "quantity": 8
    },
    {
      "id": "ed81197e-e3c6-47db-9ba2-7ea363240b1f",
      "cart_id": "38665544-ea58-48dc-9c51-3944ac9d283f",
      "product_id": "217899f7-2708-42a6-9886-152d1004c4d0",
      "name": "Intelligent Fresh Towels",
      "image_url": "https://picsum.photos/seed/W9IZDi/640/480",
      "price": "209",
      "quantity": 10
    },
    {
      "id": "31da20ae-642a-4e3c-96d6-fa8890a0198c",
      "cart_id": "38665544-ea58-48dc-9c51-3944ac9d283f",
      "product_id": "081b9380-370c-4697-9d2a-a730e0e0211b",
      "name": "Handcrafted Frozen Towels",
      "image_url": "https://picsum.photos/seed/pj7xnRJx/640/480",
      "price": "505",
      "quantity": 4
    },
    {
      "id": "a8c9d058-47ea-4e94-9c9f-865a0d22ab49",
      "cart_id": "27c4da84-58d9-486c-9849-f6f660d25394",
      "product_id": "b6e6a53a-ecf7-4760-af8d-7fcba8dd50af",
      "name": "Small Steel Chips",
      "image_url": "https://picsum.photos/seed/T0Pjh577/640/480",
      "price": "264",
      "quantity": 6
    },
    {
      "id": "2bfb33d3-e56a-49db-8518-345d3262d3b9",
      "cart_id": "27c4da84-58d9-486c-9849-f6f660d25394",
      "product_id": "b6e6a53a-ecf7-4760-af8d-7fcba8dd50af",
      "name": "Small Steel Chips",
      "image_url": "https://picsum.photos/seed/T0Pjh577/640/480",
      "price": "264",
      "quantity": 5
    },
    {
      "id": "27ea9f6d-ad1b-4959-a562-8b9a2091ef1c",
      "cart_id": "27c4da84-58d9-486c-9849-f6f660d25394",
      "product_id": "4ca383ec-cb34-44eb-bd72-8ecefec09670",
      "name": "Unbranded Metal Computer",
      "image_url": "https://picsum.photos/seed/m6MBMUZti/640/480",
      "price": "71",
      "quantity": 9
    },
    {
      "id": "bddf7e66-9d0c-49a9-9f78-283e031808c9",
      "cart_id": "27c4da84-58d9-486c-9849-f6f660d25394",
      "product_id": "7e52ad1f-d48f-4be7-812c-76f0471536a4",
      "name": "Modern Wooden Cheese",
      "image_url": "https://picsum.photos/seed/RXNE5aUCux/640/480",
      "price": "546",
      "quantity": 5
    },
    {
      "id": "1ab0f33a-a70a-470c-b314-e9ad173ff8f4",
      "cart_id": "27c4da84-58d9-486c-9849-f6f660d25394",
      "product_id": "77a8fc5d-d8ae-4896-b89a-c4097fe1c63b",
      "name": "Electronic Soft Soap",
      "image_url": "https://picsum.photos/seed/IspQCoJdSU/640/480",
      "price": "405",
      "quantity": 3
    },
    {
      "id": "8bba6ff9-ca15-4e41-9a8f-89c9733a7aaa",
      "cart_id": "e270a02a-c6a7-400d-bb8f-693f8a6c1adf",
      "product_id": "6f3b7e1c-2f36-472b-8805-86e493a83608",
      "name": "Electronic Rubber Pants",
      "image_url": "https://picsum.photos/seed/J4BFDMJ/640/480",
      "price": "483",
      "quantity": 3
    },
    {
      "id": "6d2e43e7-d304-4b2b-879a-77dc70aefb47",
      "cart_id": "e270a02a-c6a7-400d-bb8f-693f8a6c1adf",
      "product_id": "1d483375-4e59-4e51-a735-fe9e89923018",
      "name": "Elegant Steel Cheese",
      "image_url": "https://picsum.photos/seed/LD1md/640/480",
      "price": "324",
      "quantity": 6
    },
    {
      "id": "615c9208-bd4b-4ace-8117-54bae06636d2",
      "cart_id": "e270a02a-c6a7-400d-bb8f-693f8a6c1adf",
      "product_id": "7e52ad1f-d48f-4be7-812c-76f0471536a4",
      "name": "Modern Wooden Cheese",
      "image_url": "https://picsum.photos/seed/RXNE5aUCux/640/480",
      "price": "546",
      "quantity": 10
    },
    {
      "id": "34af9567-4fba-4713-9a01-633562320f1a",
      "cart_id": "e270a02a-c6a7-400d-bb8f-693f8a6c1adf",
      "product_id": "7e52ad1f-d48f-4be7-812c-76f0471536a4",
      "name": "Modern Wooden Cheese",
      "image_url": "https://picsum.photos/seed/RXNE5aUCux/640/480",
      "price": "546",
      "quantity": 5
    },
    {
      "id": "eba5fa99-d0b0-4fec-8c3a-eb2f00406d3d",
      "cart_id": "e270a02a-c6a7-400d-bb8f-693f8a6c1adf",
      "product_id": "a8be7a9e-67ee-4c9f-a5f9-4bc1cf3c4f71",
      "name": "Sleek Concrete Bacon",
      "image_url": "https://picsum.photos/seed/SiXDkURjs/640/480",
      "price": "338",
      "quantity": 7
    },
    {
      "id": "ddf54766-66ab-4a9e-be64-2f9a8c01b343",
      "cart_id": "d207be54-0700-4eea-a270-15a31d8a24e7",
      "product_id": "6f3b7e1c-2f36-472b-8805-86e493a83608",
      "name": "Electronic Rubber Pants",
      "image_url": "https://picsum.photos/seed/J4BFDMJ/640/480",
      "price": "483",
      "quantity": 8
    },
    {
      "id": "633d9d45-1617-44fe-a2ed-815848458307",
      "cart_id": "d207be54-0700-4eea-a270-15a31d8a24e7",
      "product_id": "18a1c4f0-e9d7-4898-b0cc-9fe34194f1b0",
      "name": "Elegant Fresh Table",
      "image_url": "https://picsum.photos/seed/utmXC/640/480",
      "price": "444",
      "quantity": 6
    },
    {
      "id": "00ff3c35-509e-4d48-a668-08be9e71aa38",
      "cart_id": "d207be54-0700-4eea-a270-15a31d8a24e7",
      "product_id": "7437dc59-a061-4e49-be4e-ebf3971e154e",
      "name": "Sleek Rubber Towels",
      "image_url": "https://picsum.photos/seed/FuaqTodusk/640/480",
      "price": "492",
      "quantity": 8
    },
    {
      "id": "a7abe512-e2a2-46b9-97c6-2a5470b9bee2",
      "cart_id": "d207be54-0700-4eea-a270-15a31d8a24e7",
      "product_id": "1cacbab5-0572-47e7-9a30-4df8d9813395",
      "name": "Handmade Wooden Gloves",
      "image_url": "https://picsum.photos/seed/dEnzu/640/480",
      "price": "177",
      "quantity": 7
    },
    {
      "id": "9ae4e778-5726-4ebc-aec6-5785655f39fd",
      "cart_id": "d207be54-0700-4eea-a270-15a31d8a24e7",
      "product_id": "7437dc59-a061-4e49-be4e-ebf3971e154e",
      "name": "Sleek Rubber Towels",
      "image_url": "https://picsum.photos/seed/FuaqTodusk/640/480",
      "price": "492",
      "quantity": 8
    }
  ]
}